rstl/__init__.py
rstl/stl.py
rstl-0.1.3.dist-info/METADATA
rstl-0.1.3.dist-info/RECORD
rstl-0.1.3.dist-info/WHEEL
rstl-0.1.3.dist-info/top_level.txt
