Metadata-Version: 2.1
Name: rstl
Version: 0.1.3
Summary: A Python port of R's stl function
Home-page: https://github.com/ericist/rstl
Author: Eric Rauch
Author-email: ericist@pm.me
License: UNKNOWN
Platform: UNKNOWN
Classifier: Programming Language :: Python :: 2
Classifier: Programming Language :: Python :: 3
Classifier: License :: OSI Approved :: GNU Lesser General Public License v3 (LGPLv3)
Classifier: Operating System :: OS Independent
